flask_dramatiq.py
flask_dramatiq-0.6.0.dist-info/entry_points.txt
flask_dramatiq-0.6.0.dist-info/LICENSE
flask_dramatiq-0.6.0.dist-info/WHEEL
flask_dramatiq-0.6.0.dist-info/METADATA
flask_dramatiq-0.6.0.dist-info/RECORD
