Metadata-Version: 2.1
Name: flask-dramatiq
Version: 0.6.0
Summary: Adds Dramatiq support to your Flask application
Home-page: https://pypi.org/project/flask-dramatiq
License: BSD-3-Clause
Author: Étienne BERSAC
Requires-Python: >=3.6,<4.0
Classifier: License :: OSI Approved :: BSD License
Classifier: Programming Language :: Python :: 3
Classifier: Programming Language :: Python :: 3.6
Classifier: Programming Language :: Python :: 3.7
Requires-Dist: dramatiq (>=1.5,<2.0)
Project-URL: Documentation, https://flask-dramatiq.rtfd.io
